{
  "l": "tami1289",
  "s": "Taml",
  "b": "modern",
  "m": [
    {"g": "அ", "p": "a", "c": ["i", "m", "s"]},
    {"g": "ஆ", "p": "aː", "c": "n"},
    {"g": "இ", "p": "i", "c": ["i", "m", "s"]},
    {"g": "ஈ", "p": "iː", "c": "n"},
    {"g": "உ", "p": "u", "c": ["i", "m", "s"]},
    {"g": "ஊ", "p": "uː", "c": "n"},
    {"g": "எ", "p": "e", "c": ["i", "m", "s"]},
    {"g": "ஏ", "p": "eː", "c": "n"},
    {"g": "ஐ", "p": "ai̯", "c": "n"},
    {"g": "ஒ", "p": "o", "c": ["i", "m", "s"]},
    {"g": "ஓ", "p": "oː", "c": "n"},
    {"g": "ஔ", "p": "au̯", "c": ["i", "m", "s"]},
    {"g": "ஃ", "p": "ˑ", "c": "m"},
    {"g": "க்", "p": "k", "c": ["i", "m", "f"]},
    {"g": "ங்", "p": "ŋ", "c": ["m", "f"]},
    {"g": "ச்", "p": "ʧ", "c": ["i", "m", "f"]},
    {"g": "ஞ்", "p": "ɲ", "c": ["m", "f"]},
    {"g": "ட்", "p": "ʈ", "c": ["m", "f"]},
    {"g": "ண்", "p": "ɳ", "c": ["m", "f"]},
    {"g": "த்", "p": "t̪", "c": ["i", "m", "f"]},
    {"g": "ந்", "p": "n̪", "c": ["m", "f"]},
    {"g": "ப்", "p": "p", "c": ["i", "m", "f"]},
    {"g": "ம்", "p": "m", "c": ["m", "f"]},
    {"g": "ய்", "p": "j", "c": ["m", "f"]},
    {"g": "ர்", "p": "ɾ", "c": ["m", "f"]},
    {"g": "ல்", "p": "l", "c": ["m", "f"]},
    {"g": "வ்", "p": "ʋ", "c": ["i", "m", "f"]},
    {"g": "ழ்", "p": "ɻ", "c": ["m", "f"]},
    {"g": "ள்", "p": "ɭ", "c": ["m", "f"]},
    {"g": "ற்", "p": "r", "c": ["m", "f"]},
    {"g": "ன்", "p": "n", "c": ["m", "f"]},
    {"g": "க", "p": "ka", "c": ["i", "m"]},
    {"g": "கா", "p": "kaː", "c": "n"},
    {"g": "கி", "p": "ki", "c": ["i", "m"]},
    {"g": "கீ", "p": "kiː", "c": ["i", "m"]},
    {"g": "கு", "p": "ku", "c": ["i", "m"]},
    {"g": "கூ", "p": "kuː", "c": ["i", "m"]},
    {"g": "கெ", "p": "ke", "c": ["i", "m"]},
    {"g": "கே", "p": "keː", "c": ["i", "m"]},
    {"g": "கை", "p": "kai̯", "c": "n"},
    {"g": "கொ", "p": "ko", "c": ["i", "m"]},
    {"g": "கோ", "p": "koː", "c": ["i", "m"]},
    {"g": "கௌ", "p": "kau̯", "c": ["i", "m"]},
    {"g": "ங", "p": "ŋa", "c": ["i", "m"]},
    {"g": "ஙா", "p": "ŋaː", "c": ["i", "m"]},
    {"g": "ஙி", "p": "ŋi", "c": ["i", "m"]},
    {"g": "ஙீ", "p": "ŋiː", "c": ["i", "m"]},
    {"g": "ஙு", "p": "ŋu", "c": ["i", "m"]},
    {"g": "ஙூ", "p": "ŋuː", "c": ["i", "m"]},
    {"g": "ஙெ", "p": "ŋe", "c": ["i", "m"]},
    {"g": "ஙே", "p": "ŋeː", "c": ["i", "m"]},
    {"g": "ஙை", "p": "ŋai̯", "c": ["i", "m"]},
    {"g": "ஙொ", "p": "ŋo", "c": ["i", "m"]},
    {"g": "ஙோ", "p": "ŋoː", "c": ["i", "m"]},
    {"g": "ஙௌ", "p": "ŋau̯", "c": ["i", "m"]},
    {"g": "ச", "p": "ʧa", "c": ["i", "m"]},
    {"g": "சா", "p": "ʧaː", "c": "n"},
    {"g": "சி", "p": "ʧi", "c": ["i", "m"]},
    {"g": "சீ", "p": "ʧiː", "c": ["i", "m"]},
    {"g": "சு", "p": "ʧu", "c": ["i", "m"]},
    {"g": "சூ", "p": "ʧuː", "c": ["i", "m"]},
    {"g": "செ", "p": "ʧe", "c": ["i", "m"]},
    {"g": "சே", "p": "ʧeː", "c": ["i", "m"]},
    {"g": "சை", "p": "ʧai̯", "c": ["i", "m"]},
    {"g": "சொ", "p": "ʧo", "c": ["i", "m"]},
    {"g": "சோ", "p": "ʧoː", "c": ["i", "m"]},
    {"g": "சௌ", "p": "ʧau̯", "c": ["i", "m"]},
    {"g": "ஞ", "p": "ɲa", "c": ["i", "m"]},
    {"g": "ஞா", "p": "ɲaː", "c": ["i", "m"]},
    {"g": "ஞி", "p": "ɲi", "c": ["i", "m"]},
    {"g": "ஞீ", "p": "ɲiː", "c": ["i", "m"]},
    {"g": "ஞு", "p": "ɲu", "c": ["i", "m"]},
    {"g": "ஞூ", "p": "ɲuː", "c": ["i", "m"]},
    {"g": "ஞெ", "p": "ɲe", "c": ["i", "m"]},
    {"g": "ஞே", "p": "ɲeː", "c": ["i", "m"]},
    {"g": "ஞை", "p": "ɲai̯", "c": ["i", "m"]},
    {"g": "ஞொ", "p": "ɲo", "c": ["i", "m"]},
    {"g": "ஞோ", "p": "ɲoː", "c": ["i", "m"]},
    {"g": "ஞௌ", "p": "ɲau̯", "c": ["i", "m"]},
    {"g": "ட", "p": "ʈa", "c": ["i", "m"]},
    {"g": "டா", "p": "ʈaː", "c": "n"},
    {"g": "டி", "p": "ʈi", "c": ["i", "m", "f"]},
    {"g": "டீ", "p": "ʈiː", "c": ["i", "m", "f"]},
    {"g": "டு", "p": "ʈu", "c": ["i", "m", "f"]},
    {"g": "டூ", "p": "ʈuː", "c": ["i", "m"]},
    {"g": "டெ", "p": "ʈe", "c": ["i", "m"]},
    {"g": "டே", "p": "ʈeː", "c": ["i", "m", "f"]},
    {"g": "டை", "p": "ʈai̯", "c": ["i", "m"]},
    {"g": "டொ", "p": "ʈo", "c": ["i", "m"]},
    {"g": "டோ", "p": "ʈoː", "c": ["i", "m"]},
    {"g": "டௌ", "p": "ʈau̯", "c": ["i", "m"]},
    {"g": "ண", "p": "ɳa", "c": ["i", "m"]},
    {"g": "ணா", "p": "ɳaː", "c": ["i", "m"]},
    {"g": "ணி", "p": "ɳi", "c": ["i", "m"]},
    {"g": "ணீ", "p": "ɳiː", "c": ["i", "m"]},
    {"g": "ணு", "p": "ɳu", "c": ["i", "m"]},
    {"g": "ணூ", "p": "ɳuː", "c": ["i", "m"]},
    {"g": "ணெ", "p": "ɳe", "c": ["i", "m"]},
    {"g": "ணே", "p": "ɳeː", "c": ["i", "m"]},
    {"g": "ணை", "p": "ɳai̯", "c": ["i", "m"]},
    {"g": "ணொ", "p": "ɳo", "c": ["i", "m"]},
    {"g": "ணோ", "p": "ɳoː", "c": ["i", "m"]},
    {"g": "ணௌ", "p": "ɳau̯", "c": ["i", "m"]},
    {"g": "த", "p": "t̪a", "c": ["i", "m"]},
    {"g": "தா", "p": "t̪aː", "c": ["i", "m"]},
    {"g": "தி", "p": "t̪i", "c": ["i", "m"]},
    {"g": "தீ", "p": "t̪iː", "c": ["i", "m", "f"]},
    {"g": "து", "p": "t̪u", "c": ["i", "m", "f"]},
    {"g": "தூ", "p": "t̪uː", "c": ["i", "m"]},
    {"g": "தெ", "p": "t̪e", "c": ["i", "m"]},
    {"g": "தே", "p": "t̪eː", "c": ["i", "m"]},
    {"g": "தை", "p": "t̪ai̯", "c": ["i", "m"]},
    {"g": "தொ", "p": "t̪o", "c": ["i", "m"]},
    {"g": "தோ", "p": "t̪oː", "c": ["i", "m"]},
    {"g": "தௌ", "p": "t̪au̯", "c": ["i", "m"]},
    {"g": "ந", "p": "n̪a", "c": ["i", "m"]},
    {"g": "நா", "p": "n̪aː", "c": "n"},
    {"g": "நி", "p": "n̪i", "c": ["i", "m"]},
    {"g": "நீ", "p": "n̪iː", "c": ["i", "m", "f"]},
    {"g": "நு", "p": "n̪u", "c": ["i", "m"]},
    {"g": "நூ", "p": "n̪uː", "c": ["i", "m"]},
    {"g": "நெ", "p": "n̪e", "c": ["i", "m"]},
    {"g": "நே", "p": "n̪eː", "c": ["i", "m"]},
    {"g": "நை", "p": "n̪ai̯", "c": ["i", "m"]},
    {"g": "நொ", "p": "n̪o", "c": ["i", "m"]},
    {"g": "நோ", "p": "n̪oː", "c": ["i", "m"]},
    {"g": "நௌ", "p": "n̪au̯", "c": ["i", "m"]},
    {"g": "ப", "p": "pa", "c": ["i", "m"]},
    {"g": "பா", "p": "paː", "c": "n"},
    {"g": "பி", "p": "pi", "c": ["i", "m"]},
    {"g": "பீ", "p": "piː", "c": ["i", "m"]},
    {"g": "பு", "p": "pu", "c": ["i", "m"]},
    {"g": "பூ", "p": "puː", "c": ["i", "m", "f"]},
    {"g": "பெ", "p": "pe", "c": ["i", "m"]},
    {"g": "பே", "p": "peː", "c": ["i", "m"]},
    {"g": "பை", "p": "pai̯", "c": ["i", "m", "f"]},
    {"g": "பொ", "p": "po", "c": ["i", "m"]},
    {"g": "போ", "p": "poː", "c": ["i", "m"]},
    {"g": "பௌ", "p": "pau̯", "c": ["i", "m"]},
    {"g": "ம", "p": "ma", "c": ["i", "m"]},
    {"g": "மா", "p": "maː", "c": "n"},
    {"g": "மி", "p": "mi", "c": ["i", "m"]},
    {"g": "மீ", "p": "miː", "c": ["i", "m"]},
    {"g": "மு", "p": "mu", "c": ["i", "m"]},
    {"g": "மூ", "p": "muː", "c": ["i", "m"]},
    {"g": "மெ", "p": "me", "c": ["i", "m"]},
    {"g": "மே", "p": "meː", "c": ["i", "m"]},
    {"g": "மை", "p": "mai̯", "c": ["i", "m", "f"]},
    {"g": "மொ", "p": "mo", "c": ["i", "m"]},
    {"g": "மோ", "p": "moː", "c": ["i", "m"]},
    {"g": "மௌ", "p": "mau̯", "c": ["i", "m"]},
    {"g": "ய", "p": "ja", "c": ["i", "m"]},
    {"g": "யா", "p": "jaː", "c": ["i", "m"]},
    {"g": "யி", "p": "ji", "c": ["i", "m"]},
    {"g": "யீ", "p": "jiː", "c": ["i", "m"]},
    {"g": "யு", "p": "ju", "c": ["i", "m"]},
    {"g": "யூ", "p": "juː", "c": ["i", "m"]},
    {"g": "யெ", "p": "je", "c": ["i", "m"]},
    {"g": "யே", "p": "jeː", "c": ["i", "m"]},
    {"g": "யை", "p": "jai̯", "c": ["i", "m"]},
    {"g": "யொ", "p": "jo", "c": ["i", "m"]},
    {"g": "யோ", "p": "joː", "c": ["i", "m"]},
    {"g": "யௌ", "p": "jau̯", "c": ["i", "m"]},
    {"g": "ர", "p": "ɾa", "c": ["i", "m"]},
    {"g": "ரா", "p": "ɾaː", "c": "n"},
    {"g": "ரி", "p": "ɾi", "c": ["i", "m"]},
    {"g": "ரீ", "p": "ɾiː", "c": ["i", "m"]},
    {"g": "ரு", "p": "ɾu", "c": ["i", "m"]},
    {"g": "ரூ", "p": "ɾuː", "c": ["i", "m", "f"]},
    {"g": "ரெ", "p": "ɾe", "c": ["i", "m"]},
    {"g": "ரே", "p": "ɾeː", "c": ["i", "m"]},
    {"g": "ரை", "p": "ɾai̯", "c": ["i", "m"]},
    {"g": "ரொ", "p": "ɾo", "c": ["i", "m"]},
    {"g": "ரோ", "p": "ɾoː", "c": ["i", "m"]},
    {"g": "ரௌ", "p": "ɾau̯", "c": ["i", "m"]},
    {"g": "ல", "p": "la", "c": ["i", "m"]},
    {"g": "லா", "p": "laː", "c": "n"},
    {"g": "லி", "p": "li", "c": ["i", "m", "f"]},
    {"g": "லீ", "p": "liː", "c": ["i", "m"]},
    {"g": "லு", "p": "lu", "c": ["i", "m"]},
    {"g": "லூ", "p": "luː", "c": ["i", "m"]},
    {"g": "லெ", "p": "le", "c": ["i", "m"]},
    {"g": "லே", "p": "leː", "c": ["i", "m"]},
    {"g": "லை", "p": "lai̯", "c": ["i", "m"]},
    {"g": "லொ", "p": "lo", "c": ["i", "m"]},
    {"g": "லோ", "p": "loː", "c": ["i", "m"]},
    {"g": "லௌ", "p": "lau̯", "c": ["i", "m"]},
    {"g": "வ", "p": "ʋa", "c": ["i", "m"]},
    {"g": "வா", "p": "ʋaː", "c": "n"},
    {"g": "வி", "p": "ʋi", "c": ["i", "m"]},
    {"g": "வீ", "p": "ʋiː", "c": ["i", "m"]},
    {"g": "வு", "p": "ʋu", "c": ["i", "m"]},
    {"g": "வூ", "p": "ʋuː", "c": ["i", "m"]},
    {"g": "வெ", "p": "ʋe", "c": ["i", "m"]},
    {"g": "வே", "p": "ʋeː", "c": ["i", "m"]},
    {"g": "வை", "p": "ʋai̯", "c": ["i", "m"]},
    {"g": "வொ", "p": "ʋo", "c": ["i", "m"]},
    {"g": "வோ", "p": "ʋoː", "c": ["i", "m"]},
    {"g": "வௌ", "p": "ʋau̯", "c": ["i", "m"]},
    {"g": "ழ", "p": "ɻa", "c": ["i", "m"]},
    {"g": "ழா", "p": "ɻaː", "c": ["i", "m"]},
    {"g": "ழி", "p": "ɻi", "c": ["i", "m"]},
    {"g": "ழீ", "p": "ɻiː", "c": ["i", "m"]},
    {"g": "ழு", "p": "ɻu", "c": ["i", "m"]},
    {"g": "ழூ", "p": "ɻuː", "c": ["i", "m"]},
    {"g": "ழெ", "p": "ɻe", "c": ["i", "m"]},
    {"g": "ழே", "p": "ɻeː", "c": ["i", "m"]},
    {"g": "ழை", "p": "ɻai̯", "c": ["i", "m"]},
    {"g": "ழொ", "p": "ɻo", "c": ["i", "m"]},
    {"g": "ழோ", "p": "ɻoː", "c": ["i", "m"]},
    {"g": "ழௌ", "p": "ɻau̯", "c": ["i", "m"]},
    {"g": "ள", "p": "ɭa", "c": ["i", "m"]},
    {"g": "ளா", "p": "ɭaː", "c": ["i", "m"]},
    {"g": "ளி", "p": "ɭi", "c": ["i", "m"]},
    {"g": "ளீ", "p": "ɭiː", "c": ["i", "m"]},
    {"g": "ளு", "p": "ɭu", "c": ["i", "m"]},
    {"g": "ளூ", "p": "ɭuː", "c": ["i", "m"]},
    {"g": "ளெ", "p": "ɭe", "c": ["i", "m"]},
    {"g": "ளே", "p": "ɭeː", "c": ["i", "m"]},
    {"g": "ளை", "p": "ɭai̯", "c": ["i", "m"]},
    {"g": "ளொ", "p": "ɭo", "c": ["i", "m"]},
    {"g": "ளோ", "p": "ɭoː", "c": ["i", "m"]},
    {"g": "ளௌ", "p": "ɭau̯", "c": ["i", "m"]},
    {"g": "ற", "p": "ra", "c": ["i", "m"]},
    {"g": "றா", "p": "raː", "c": ["i", "m"]},
    {"g": "றி", "p": "ri", "c": ["i", "m"]},
    {"g": "றீ", "p": "riː", "c": ["i", "m"]},
    {"g": "று", "p": "ru", "c": ["i", "m", "f"]},
    {"g": "றூ", "p": "ruː", "c": ["i", "m"]},
    {"g": "றெ", "p": "re", "c": ["i", "m"]},
    {"g": "றே", "p": "reː", "c": ["i", "m"]},
    {"g": "றை", "p": "rai̯", "c": ["i", "m"]},
    {"g": "றொ", "p": "ro", "c": ["i", "m"]},
    {"g": "றோ", "p": "roː", "c": ["i", "m"]},
    {"g": "றௌ", "p": "rau̯", "c": ["i", "m"]},
    {"g": "ன", "p": "na", "c": ["i", "m"]},
    {"g": "னா", "p": "naː", "c": ["i", "m"]},
    {"g": "னி", "p": "ni", "c": ["i", "m"]},
    {"g": "னீ", "p": "niː", "c": ["i", "m"]},
    {"g": "னு", "p": "nu", "c": ["i", "m"]},
    {"g": "னூ", "p": "nuː", "c": ["i", "m"]},
    {"g": "னெ", "p": "ne", "c": ["i", "m"]},
    {"g": "னே", "p": "neː", "c": ["i", "m"]},
    {"g": "னை", "p": "nai̯", "c": ["i", "m"]},
    {"g": "னொ", "p": "no", "c": ["i", "m"]},
    {"g": "னோ", "p": "noː", "c": ["i", "m"]},
    {"g": "னௌ", "p": "nau̯", "c": ["i", "m"]}
  ]
}
